{
  "version": "6",
  "dialect": "sqlite",
  "id": "ab32e5a6-3179-4d3a-992c-4f9a2cda7756",
  "prevId": "7a80d588-ee40-4467-a4fe-c6fd9cc5e5e1",
  "tables": {
    "workshop_submissions": {
      "name": "workshop_submissions",
      "columns": {
        "id": {
          "name": "id",
          "type": "text",
          "primaryKey": true,
          "notNull": true,
          "autoincrement": false
        },
        "plant": {
          "name": "plant",
          "type": "text",
          "primaryKey": false,
          "notNull": true,
          "autoincrement": false
        },
        "submitter_name": {
          "name": "submitter_name",
          "type": "text",
          "primaryKey": false,
          "notNull": true,
          "autoincrement": false,
          "default": "''"
        },
        "submitter_email": {
          "name": "submitter_email",
          "type": "text",
          "primaryKey": false,
          "notNull": true,
          "autoincrement": false,
          "default": "''"
        },
        "designation": {
          "name": "designation",
          "type": "text",
          "primaryKey": false,
          "notNull": true,
          "autoincrement": false,
          "default": "''"
        },
        "use_case_1": {
          "name": "use_case_1",
          "type": "text",
          "primaryKey": false,
          "notNull": true,
          "autoincrement": false,
          "default": "''"
        },
        "use_case_2": {
          "name": "use_case_2",
          "type": "text",
          "primaryKey": false,
          "notNull": true,
          "autoincrement": false,
          "default": "''"
        },
        "use_case_3": {
          "name": "use_case_3",
          "type": "text",
          "primaryKey": false,
          "notNull": true,
          "autoincrement": false,
          "default": "''"
        },
        "use_case_4": {
          "name": "use_case_4",
          "type": "text",
          "primaryKey": false,
          "notNull": true,
          "autoincrement": false,
          "default": "''"
        },
        "value_stream_1_selected": {
          "name": "value_stream_1_selected",
          "type": "integer",
          "primaryKey": false,
          "notNull": true,
          "autoincrement": false,
          "default": false
        },
        "value_stream_2_selected": {
          "name": "value_stream_2_selected",
          "type": "integer",
          "primaryKey": false,
          "notNull": true,
          "autoincrement": false,
          "default": false
        },
        "value_stream_3_selected": {
          "name": "value_stream_3_selected",
          "type": "integer",
          "primaryKey": false,
          "notNull": true,
          "autoincrement": false,
          "default": false
        },
        "value_stream_4_selected": {
          "name": "value_stream_4_selected",
          "type": "integer",
          "primaryKey": false,
          "notNull": true,
          "autoincrement": false,
          "default": false
        },
        "expected_benefits": {
          "name": "expected_benefits",
          "type": "text",
          "primaryKey": false,
          "notNull": true,
          "autoincrement": false,
          "default": "''"
        },
        "status": {
          "name": "status",
          "type": "text",
          "primaryKey": false,
          "notNull": true,
          "autoincrement": false,
          "default": "'draft'"
        },
        "is_visible": {
          "name": "is_visible",
          "type": "integer",
          "primaryKey": false,
          "notNull": true,
          "autoincrement": false,
          "default": false
        },
        "created_at": {
          "name": "created_at",
          "type": "text",
          "primaryKey": false,
          "notNull": true,
          "autoincrement": false,
          "default": "CURRENT_TIMESTAMP"
        },
        "updated_at": {
          "name": "updated_at",
          "type": "text",
          "primaryKey": false,
          "notNull": true,
          "autoincrement": false,
          "default": "CURRENT_TIMESTAMP"
        },
        "submitted_at": {
          "name": "submitted_at",
          "type": "text",
          "primaryKey": false,
          "notNull": false,
          "autoincrement": false
        },
        "reviewed_at": {
          "name": "reviewed_at",
          "type": "text",
          "primaryKey": false,
          "notNull": false,
          "autoincrement": false
        }
      },
      "indexes": {
        "workshop_submissions_plant_idx": {
          "name": "workshop_submissions_plant_idx",
          "columns": [
            "plant"
          ],
          "isUnique": false
        },
        "workshop_submissions_status_visibility_idx": {
          "name": "workshop_submissions_status_visibility_idx",
          "columns": [
            "status",
            "is_visible"
          ],
          "isUnique": false
        },
        "workshop_submissions_created_at_idx": {
          "name": "workshop_submissions_created_at_idx",
          "columns": [
            "created_at"
          ],
          "isUnique": false
        }
      },
      "foreignKeys": {},
      "compositePrimaryKeys": {},
      "uniqueConstraints": {},
      "checkConstraints": {
        "workshop_submissions_plant_check": {
          "name": "workshop_submissions_plant_check",
          "value": "\"workshop_submissions\".\"plant\" in ('Panipat', 'Ludhiana', 'Cheyyar', 'Chamarajanagar', 'Mahad', 'Kharagpur')"
        },
        "workshop_submissions_status_check": {
          "name": "workshop_submissions_status_check",
          "value": "\"workshop_submissions\".\"status\" in ('draft', 'submitted', 'approved', 'rejected')"
        },
        "workshop_submissions_visibility_check": {
          "name": "workshop_submissions_visibility_check",
          "value": "\"workshop_submissions\".\"is_visible\" in (0, 1)"
        }
      }
    }
  },
  "views": {},
  "enums": {},
  "_meta": {
    "schemas": {},
    "tables": {},
    "columns": {}
  },
  "internal": {
    "indexes": {}
  }
}